led_matrix_testsim.v
// ============================================================================
// ICN2038S LED Matrix Controller - VERSIÓN FUNCIONAL PARA SIMULACIÓN
// ============================================================================

module led_matrix_testsim (
    input wire clk_25mhz,
    output reg LP_CLK,
    output reg LATCH,
    output reg NOE,
    output reg [2:0] RGB0,
    output reg [2:0] RGB1,
    output reg [4:0] ROW
);

// ============================================================================
// Parámetros
// ============================================================================
parameter NUM_ROWS = 32;
parameter NUM_COLS = 64;
parameter BIT_DEPTH = 4;

// Estados principales
localparam INIT          = 5'd0;
localparam CONFIG_REG1   = 5'd1;
localparam CONFIG_REG2   = 5'd2;
localparam IDLE          = 5'd3;
localparam LOAD_ROW      = 5'd4;
localparam SHIFT_DATA    = 5'd5;
localparam DATA_LATCH    = 5'd6;
localparam DISPLAY       = 5'd7;
localparam NEXT_BIT      = 5'd8;
localparam NEXT_ROW      = 5'd9;

reg [4:0] state = INIT;

// Contadores - TODOS INICIALIZADOS
reg [15:0] display_counter = 0;
reg [7:0] col_counter = 0;
reg [5:0] row_counter = 0;
reg [2:0] bit_plane = 0;
reg [3:0] le_pulse_count = 0;

// Reset y clock enable - TODOS INICIALIZADOS
reg rst_n = 0;
reg [7:0] rst_counter = 0;
reg clk_en = 0;
reg [2:0] clk_div = 0;

// Flags - TODOS INICIALIZADOS
reg config_done = 0;

// ============================================================================
// Memoria de imagen
// ============================================================================
wire [5:0] actual_col = col_counter[5:0];
wire [10:0] pixel_addr = {row_counter[4:0], actual_col};  // 0-2047

wire [23:0] mem_data;
reg mem_rd = 0;

// UNA sola instancia de memoria
memory #(
    .size(2047),
    .width(10)
) mem_single (
    .clk(clk_25mhz),
    .address(pixel_addr),
    .rd(mem_rd),
    .rdata(mem_data)
);

// ============================================================================
// Extracción de datos
// ============================================================================
wire [7:0] pixel_r0_full = mem_data[23:16];
wire [7:0] pixel_g0_full = mem_data[15:8];
wire [7:0] pixel_b0_full = mem_data[7:0];

// Convertir a 4 bits (tomar bits superiores)
wire [3:0] pixel_r0 = pixel_r0_full[7:4];
wire [3:0] pixel_g0 = pixel_g0_full[7:4];
wire [3:0] pixel_b0 = pixel_b0_full[7:4];

// Para RGB1, usar los bits inferiores
wire [3:0] pixel_r1 = pixel_r0_full[3:0];
wire [3:0] pixel_g1 = pixel_g0_full[3:0];
wire [3:0] pixel_b1 = pixel_b0_full[3:0];

// Seleccionar bit según bit_plane
wire bit_r0 = pixel_r0[bit_plane];
wire bit_g0 = pixel_g0[bit_plane];
wire bit_b0 = pixel_b0[bit_plane];
wire bit_r1 = pixel_r1[bit_plane];
wire bit_g1 = pixel_g1[bit_plane];
wire bit_b1 = pixel_b1[bit_plane];

// ============================================================================
// Reset interno
// ============================================================================
always @(posedge clk_25mhz) begin
    if (rst_counter < 8'd255) begin
        rst_counter <= rst_counter + 1;
        rst_n <= 0;
    end else begin
        rst_n <= 1;
    end
end

// ============================================================================
// Clock divider
// ============================================================================
always @(posedge clk_25mhz) begin
    clk_div <= clk_div + 1;
    clk_en <= (clk_div == 3'd0);
end

// ============================================================================
// Máquina de estados principal - CORREGIDA
// ============================================================================
always @(posedge clk_25mhz) begin
    if (!rst_n) begin
        state <= INIT;
        LP_CLK <= 0;
        LATCH <= 0;
        NOE <= 1;
        RGB0 <= 3'b000;
        RGB1 <= 3'b000;
        ROW <= 5'b00000;
        col_counter <= 0;
        row_counter <= 0;
        bit_plane <= 0;
        display_counter <= 0;
        le_pulse_count <= 0;
        mem_rd <= 0;
        config_done <= 0;
    end else if (clk_en) begin
        // Reset de señales por defecto
        LP_CLK <= 0;
        LATCH <= 0;
        NOE <= 1;
        RGB0 <= 3'b000;
        RGB1 <= 3'b000;
        
        case (state)
            INIT: begin
                state <= config_done ? IDLE : CONFIG_REG1;
            end
            
            CONFIG_REG1: begin
                if (le_pulse_count < 11) begin
                    LP_CLK <= ~LP_CLK;
                    LATCH <= 1;
                    
                    if (LP_CLK) begin
                        RGB0 <= 3'b000;
                        RGB1 <= 3'b000;
                        le_pulse_count <= le_pulse_count + 1;
                    end
                end else begin
                    LATCH <= 0;
                    LP_CLK <= 0;
                    le_pulse_count <= 0;
                    state <= CONFIG_REG2;
                end
            end
            
            CONFIG_REG2: begin
                if (le_pulse_count < 12) begin
                    LP_CLK <= ~LP_CLK;
                    LATCH <= 1;
                    
                    if (LP_CLK) begin
                        RGB0 <= 3'b000;
                        RGB1 <= 3'b000;
                        le_pulse_count <= le_pulse_count + 1;
                    end
                end else begin
                    LATCH <= 0;
                    LP_CLK <= 0;
                    le_pulse_count <= 0;
                    config_done <= 1;
                    state <= IDLE;
                end
            end
            
            IDLE: begin
                mem_rd <= 1;
                state <= LOAD_ROW;
            end
            
            LOAD_ROW: begin
                mem_rd <= 1;
                ROW <= row_counter[4:0];
                col_counter <= 0;
                state <= SHIFT_DATA;
            end
            
            SHIFT_DATA: begin
                if (col_counter < NUM_COLS) begin
                    LP_CLK <= ~LP_CLK;
                    
                    if (LP_CLK == 0) begin
                        // Enviar datos a RGB0 y RGB1
                        RGB0[0] <= bit_r0;
                        RGB0[1] <= bit_g0;
                        RGB0[2] <= bit_b0;
                        RGB1[0] <= bit_r1;
                        RGB1[1] <= bit_g1;
                        RGB1[2] <= bit_b1;
                    end else begin
                        col_counter <= col_counter + 1;
                    end
                end else begin
                    LP_CLK <= 0;
                    RGB0 <= 3'b000;
                    RGB1 <= 3'b000;
                    mem_rd <= 0;
                    le_pulse_count <= 0;
                    state <= DATA_LATCH;
                end
            end
            
            DATA_LATCH: begin
                if (le_pulse_count < 3) begin
                    LP_CLK <= ~LP_CLK;
                    LATCH <= 1;
                    
                    if (LP_CLK) begin
                        le_pulse_count <= le_pulse_count + 1;
                    end
                end else begin
                    LATCH <= 0;
                    LP_CLK <= 0;
                    le_pulse_count <= 0;
                    display_counter <= 0;
                    state <= DISPLAY;
                end
            end
            
            DISPLAY: begin
                NOE <= 0;
                display_counter <= display_counter + 1;
                
                case (bit_plane)
                    3'd0: if (display_counter >= 16'd50)   state <= NEXT_BIT;
                    3'd1: if (display_counter >= 16'd100)  state <= NEXT_BIT;
                    3'd2: if (display_counter >= 16'd200)  state <= NEXT_BIT;
                    3'd3: if (display_counter >= 16'd400)  state <= NEXT_BIT;
                    default: state <= NEXT_BIT;
                endcase
            end
            
            NEXT_BIT: begin
                NOE <= 1;
                
                if (bit_plane >= 3) begin
                    bit_plane <= 0;
                    state <= NEXT_ROW;
                end else begin
                    bit_plane <= bit_plane + 1;
                    state <= IDLE;
                end
            end
            
            NEXT_ROW: begin
                if (row_counter >= (NUM_ROWS - 1)) begin
                    row_counter <= 0;
                end else begin
                    row_counter <= row_counter + 1;
                end
                state <= IDLE;
            end
            
            default: state <= INIT;
        endcase
    end
end

endmodule

// ============================================================================
// Módulo de memoria
// ============================================================================
module memory #(
    parameter size = 2047,
    parameter width = 10
)(
    input clk,
    input [width:0] address,
    input rd,
    output reg [23:0] rdata
);

reg [23:0] MEM [0:size];

initial begin
    $readmemh("image.hex", MEM);
end

always @(negedge clk) begin
    if (rd) begin
        rdata <= MEM[address];
    end
end

endmodule

tb_working.v
`timescale 1ns / 1ps

module tb_working;
    reg clk_25mhz = 0;
    
    // Señales del módulo
    wire LP_CLK, LATCH, NOE;
    wire [2:0] RGB0, RGB1;
    wire [4:0] ROW;
    
    // Instancia del módulo corregido
    led_matrix_testsim dut (
        .clk_25mhz(clk_25mhz),
        .LP_CLK(LP_CLK),
        .LATCH(LATCH),
        .NOE(NOE),
        .RGB0(RGB0),
        .RGB1(RGB1),
        .ROW(ROW)
    );
    
    // Contador de ciclos
    integer cycle_count = 0;
    
    // Generador de reloj (25MHz = periodo 40ns)
    always #20 begin
        clk_25mhz = ~clk_25mhz;
        if (clk_25mhz == 1) cycle_count = cycle_count + 1;
    end
    
    // Monitoreo en consola
    always @(posedge clk_25mhz) begin
        if (cycle_count == 256) begin
            $display("=== CICLO 256 ===");
            $display("rst_n = %b", dut.rst_n);
            $display("state = %d", dut.state);
            $display("config_done = %b", dut.config_done);
        end
        
        if (cycle_count == 512) begin
            $display("=== CICLO 512 ===");
            $display("state = %d", dut.state);
            $display("row_counter = %d", dut.row_counter);
            $display("col_counter = %d", dut.col_counter);
        end
        
        // Mostrar progreso cada 1000 ciclos
        if (cycle_count % 1000 == 0 && cycle_count > 0) begin
            $display("Ciclo %6d: state=%d, row=%d, col=%d, bit_plane=%d", 
                     cycle_count, dut.state, dut.row_counter, dut.col_counter, dut.bit_plane);
        end
    end
    
    initial begin
        // Archivo de volcado
        $dumpfile("working.vcd");
        $dumpvars(0, tb_working);
        
        $display("========================================");
        $display("INICIANDO SIMULACIÓN LED MATRIX CONTROLLER");
        $display("========================================");
        
        // Simular por tiempo suficiente (2ms)
        #2000000;
        
        $display("\n========================================");
        $display("SIMULACIÓN COMPLETADA");
        $display("Ciclos totales: %d", cycle_count);
        $display("Estado final: %d", dut.state);
        $display("Última fila: %d", dut.ROW);
        $display("========================================");
        
        $finish;
    end
    
    // Terminar si hay algún error crítico
    always @(posedge clk_25mhz) begin
        if (cycle_count > 300 && dut.state === 5'bx) begin
            $display("ERROR: Estado 'state' sigue en X después de 300 ciclos!");
            $display("rst_n = %b, rst_counter = %d", dut.rst_n, dut.rst_counter);
            $finish;
        end
    end
endmodule

working.vcd
$date
	Tue Dec  9 08:50:29 2025
$end
$version
	Icarus Verilog
$end
$timescale
	1ps
$end
$scope module tb_working $end
$var wire 5 ! ROW [4:0] $end
$var wire 3 " RGB1 [2:0] $end
$var wire 3 # RGB0 [2:0] $end
$var wire 1 $ NOE $end
$var wire 1 % LP_CLK $end
$var wire 1 & LATCH $end
$var reg 1 ' clk_25mhz $end
$var integer 32 ( cycle_count [31:0] $end
$scope module dut $end
$var wire 1 ' clk_25mhz $end
$var wire 4 ) pixel_r1 [3:0] $end
$var wire 8 * pixel_r0_full [7:0] $end
$var wire 4 + pixel_r0 [3:0] $end
$var wire 4 , pixel_g1 [3:0] $end
$var wire 8 - pixel_g0_full [7:0] $end
$var wire 4 . pixel_g0 [3:0] $end
$var wire 4 / pixel_b1 [3:0] $end
$var wire 8 0 pixel_b0_full [7:0] $end
$var wire 4 1 pixel_b0 [3:0] $end
$var wire 11 2 pixel_addr [10:0] $end
$var wire 24 3 mem_data [23:0] $end
$var wire 1 4 bit_r1 $end
$var wire 1 5 bit_r0 $end
$var wire 1 6 bit_g1 $end
$var wire 1 7 bit_g0 $end
$var wire 1 8 bit_b1 $end
$var wire 1 9 bit_b0 $end
$var wire 6 : actual_col [5:0] $end
$var parameter 32 ; BIT_DEPTH $end
$var parameter 5 < CONFIG_REG1 $end
$var parameter 5 = CONFIG_REG2 $end
$var parameter 5 > DATA_LATCH $end
$var parameter 5 ? DISPLAY $end
$var parameter 5 @ IDLE $end
$var parameter 5 A INIT $end
$var parameter 5 B LOAD_ROW $end
$var parameter 5 C NEXT_BIT $end
$var parameter 5 D NEXT_ROW $end
$var parameter 32 E NUM_COLS $end
$var parameter 32 F NUM_ROWS $end
$var parameter 5 G SHIFT_DATA $end
$var reg 1 & LATCH $end
$var reg 1 % LP_CLK $end
$var reg 1 $ NOE $end
$var reg 3 H RGB0 [2:0] $end
$var reg 3 I RGB1 [2:0] $end
$var reg 5 J ROW [4:0] $end
$var reg 3 K bit_plane [2:0] $end
$var reg 3 L clk_div [2:0] $end
$var reg 1 M clk_en $end
$var reg 8 N col_counter [7:0] $end
$var reg 1 O config_done $end
$var reg 16 P display_counter [15:0] $end
$var reg 4 Q le_pulse_count [3:0] $end
$var reg 1 R mem_rd $end
$var reg 6 S row_counter [5:0] $end
$var reg 8 T rst_counter [7:0] $end
$var reg 1 U rst_n $end
$var reg 5 V state [4:0] $end
$scope module mem_single $end
$var wire 11 W address [10:0] $end
$var wire 1 ' clk $end
$var wire 1 R rd $end
$var parameter 32 X size $end
$var parameter 32 Y width $end
$var reg 24 Z rdata [23:0] $end
$upscope $end
$upscope $end
$upscope $end
$enddefinitions $end
$comment Show the parameter values. $end
$dumpall
b1010 Y
b11111111111 X
b101 G
b100000 F
b1000000 E
b1001 D
b1000 C
b100 B
b0 A
b11 @
b111 ?
b110 >
b10 =
b1 <
b100 ;
$end
#0
$dumpvars
bx Z
b0 W
b0 V
0U
b0 T
b0 S
0R
b0 Q
b0 P
0O
b0 N
0M
b0 L
b0 K
bx J
bx I
bx H
b0 :
x9
x8
x7
x6
x5
x4
bx 3
b0 2
bx 1
bx 0
bx /
bx .
bx -
bx ,
bx +
bx *
bx )
b0 (
0'
x&
x%
x$
bx #
bx "
bx !
$end
#20000
b1 T
1M
b1 L
b0 !
b0 J
b0 "
b0 I
b0 #
b0 H
1$
0&
0%
b1 (
1'
#40000
0'
#60000
0M
b10 L
b10 T
b10 (
1'
#80000
0'
#100000
b11 T
b11 L
b11 (
1'
#120000
0'
#140000
b100 L
b100 T
b100 (
1'
#160000
0'
#180000
b101 T
b101 L
b101 (
1'
#200000
0'
#220000
b110 L
b110 T
b110 (
1'
#240000
0'
#260000
b111 T
b111 L
b111 (
1'
#280000
0'
#300000
b0 L
b1000 T
b1000 (
1'
#320000
0'
#340000
b1001 T
1M
b1 L
b1001 (
1'
#360000
0'
#380000
0M
b10 L
b1010 T
b1010 (
1'
#400000
0'
#420000
b1011 T
b11 L
b1011 (
1'
#440000
0'
#460000
b100 L
b1100 T
b1100 (
1'
#480000
0'
#500000
b1101 T
b101 L
b1101 (
1'
#520000
0'
#540000
b110 L
b1110 T
b1110 (
1'
#560000
0'
#580000
b1111 T
b111 L
b1111 (
1'
#600000
0'
#620000
b0 L
b10000 T
b10000 (
1'
#640000
0'
#660000
b10001 T
1M
b1 L
b10001 (
1'
#680000
0'
#700000
0M
b10 L
b10010 T
b10010 (
1'
#720000
0'
#740000
b10011 T
b11 L
b10011 (
1'
#760000
0'
#780000
b100 L
b10100 T
b10100 (
1'
#800000
0'
#820000
b10101 T
b101 L
b10101 (
1'
#840000
0'
#860000
b110 L
b10110 T
b10110 (
1'
#880000
0'
#900000
b10111 T
b111 L
b10111 (
1'
#920000
0'
#940000
b0 L
b11000 T
b11000 (
1'
#960000
0'
#980000
b11001 T
1M
b1 L
b11001 (
1'
#1000000
0'
#1020000
0M
b10 L
b11010 T
b11010 (
1'
#1040000
0'
#1060000
b11011 T
b11 L
b11011 (
1'
#1080000
0'
#1100000
b100 L
b11100 T
b11100 (
1'
#1120000
0'
#1140000
b11101 T
b101 L
b11101 (
1'
#1160000
0'
#1180000
b110 L
b11110 T
b11110 (
1'
#1200000
0'
#1220000
b11111 T
b111 L
b11111 (
1'
#1240000
0'
#1260000
b0 L
b100000 T
b100000 (
1'
#1280000
0'
#1300000
b100001 T
1M
b1 L
b100001 (
1'
#1320000
0'
#1340000
0M
b10 L
b100010 T
b100010 (
1'
#1360000
0'
#1380000
b100011 T
b11 L
b100011 (
1'
#1400000
0'
#1420000
b100 L
b100100 T
b100100 (
1'
#1440000
0'
#1460000
b100101 T
b101 L
b100101 (
1'
#1480000
0'
#1500000
b110 L
b100110 T
b100110 (
1'
#1520000
0'
#1540000
b100111 T
b111 L
b100111 (
1'
#1560000
0'
#1580000
b0 L
b101000 T
b101000 (
1'
#1600000
0'
#1620000
b101001 T
1M
b1 L
b101001 (
1'
#1640000
0'
#1660000
0M
b10 L
b101010 T
b101010 (
1'
#1680000
0'
#1700000
b101011 T
b11 L
b101011 (
1'
#1720000
0'
#1740000
b100 L
b101100 T
b101100 (
1'
#1760000
0'
#1780000
b101101 T
b101 L
b101101 (
1'
#1800000
0'
#1820000
b110 L
b101110 T
b101110 (
1'
#1840000
0'
#1860000
b101111 T
b111 L
b101111 (
1'
#1880000
0'
#1900000
b0 L
b110000 T
b110000 (
1'
#1920000
0'
#1940000
b110001 T
1M
b1 L
b110001 (
1'
#1960000
0'
#1980000
0M
b10 L
b110010 T
b110010 (
1'
#2000000
0'
#2020000
b110011 T
b11 L
b110011 (
1'
#2040000
0'
#2060000
b100 L
b110100 T
b110100 (
1'
#2080000
0'
#2100000
b110101 T
b101 L
b110101 (
1'
#2120000
0'
#2140000
b110 L
b110110 T
b110110 (
1'
#2160000
0'
#2180000
b110111 T
b111 L
b110111 (
1'
#2200000
0'
#2220000
b0 L
b111000 T
b111000 (
1'
#2240000
0'
#2260000
b111001 T
1M
b1 L
b111001 (
1'
#2280000
0'
#2300000
0M
b10 L
b111010 T
b111010 (
1'
#2320000
0'
#2340000
b111011 T
b11 L
b111011 (
1'
#2360000
0'
#2380000
b100 L
b111100 T
b111100 (
1'
#2400000
0'
#2420000
b111101 T
b101 L
b111101 (
1'
#2440000
0'
#2460000
b110 L
b111110 T
b111110 (
1'
#2480000
0'
#2500000
b111111 T
b111 L
b111111 (
1'
#2520000
0'
#2540000
b0 L
b1000000 T
b1000000 (
1'
#2560000
0'
#2580000
b1000001 T
1M
b1 L
b1000001 (
1'
#2600000
0'
#2620000
0M
b10 L
b1000010 T
b1000010 (
1'
#2640000
0'
#2660000
b1000011 T
b11 L
b1000011 (
1'
#2680000
0'
#2700000
b100 L
b1000100 T
b1000100 (
1'
#2720000
0'
#2740000
b1000101 T
b101 L
b1000101 (
1'
#2760000
0'
#2780000
b110 L
b1000110 T
b1000110 (
1'
#2800000
0'
#2820000
b1000111 T
b111 L
b1000111 (
1'
#2840000
0'
#2860000
b0 L
b1001000 T
b1001000 (
1'
#2880000
0'
#2900000
b1001001 T
1M
b1 L
b1001001 (
1'
#2920000
0'
#2940000
0M
b10 L
b1001010 T
b1001010 (
1'
#2960000
0'
#2980000
b1001011 T
b11 L
b1001011 (
1'
#3000000
0'
#3020000
b100 L
b1001100 T
b1001100 (
1'
#3040000
0'
#3060000
b1001101 T
b101 L
b1001101 (
1'
#3080000
0'
#3100000
b110 L
b1001110 T
b1001110 (
1'
#3120000
0'
#3140000
b1001111 T
b111 L
b1001111 (
1'
#3160000
0'
#3180000
b0 L
b1010000 T
b1010000 (
1'
#3200000
0'
#3220000
b1010001 T
1M
b1 L
b1010001 (
1'
#3240000
0'
#3260000
0M
b10 L
b1010010 T
b1010010 (
1'
#3280000
0'
#3300000
b1010011 T
b11 L
b1010011 (
1'
#3320000
0'
#3340000
b100 L
b1010100 T
b1010100 (
1'
#3360000
0'
#3380000
b1010101 T
b101 L
b1010101 (
1'
#3400000
0'
#3420000
b110 L
b1010110 T
b1010110 (
1'
#3440000
0'
#3460000
b1010111 T
b111 L
b1010111 (
1'
#3480000
0'
#3500000
b0 L
b1011000 T
b1011000 (
1'
#3520000
0'
#3540000
b1011001 T
1M
b1 L
b1011001 (
1'
#3560000
0'
#3580000
0M
b10 L
b1011010 T
b1011010 (
1'
#3600000
0'
#3620000
b1011011 T
b11 L
b1011011 (
1'
#3640000
0'
#3660000
b100 L
b1011100 T
b1011100 (
1'
#3680000
0'
#3700000
b1011101 T
b101 L
b1011101 (
1'
#3720000
0'
#3740000
b110 L
b1011110 T
b1011110 (
1'
#3760000
0'
#3780000
b1011111 T
b111 L
b1011111 (
1'
#3800000
0'
#3820000
b0 L
b1100000 T
b1100000 (
1'
#3840000
0'
#3860000
b1100001 T
1M
b1 L
b1100001 (
1'
#3880000
0'
#3900000
0M
b10 L
b1100010 T
b1100010 (
1'
#3920000
0'
#3940000
b1100011 T
b11 L
b1100011 (
1'
#3960000
0'
#3980000
b100 L
b1100100 T
b1100100 (
1'
#4000000
0'
#4020000
b1100101 T
b101 L
b1100101 (
1'
#4040000
0'
#4060000
b110 L
b1100110 T
b1100110 (
1'
#4080000
0'
#4100000
b1100111 T
b111 L
b1100111 (
1'
#4120000
0'
#4140000
b0 L
b1101000 T
b1101000 (
1'
#4160000
0'
#4180000
b1101001 T
1M
b1 L
b1101001 (
1'
#4200000
0'
#4220000
0M
b10 L
b1101010 T
b1101010 (
1'
#4240000
0'
#4260000
b1101011 T
b11 L
b1101011 (
1'
#4280000
0'
#4300000
b100 L
b1101100 T
b1101100 (
1'
#4320000
0'
#4340000
b1101101 T
b101 L
b1101101 (
1'
#4360000
0'
#4380000
b110 L
b1101110 T
b1101110 (
1'
#4400000
0'
#4420000
b1101111 T
b111 L
b1101111 (
1'
#4440000
0'
#4460000
b0 L
b1110000 T
b1110000 (
1'
#4480000
0'
#4500000
b1110001 T
1M
b1 L
b1110001 (
1'
#4520000
0'
#4540000
0M
b10 L
b1110010 T
b1110010 (
1'
#4560000
0'
#4580000
b1110011 T
b11 L
b1110011 (
1'
#4600000
0'
#4620000
b100 L
b1110100 T
b1110100 (
1'
#4640000
0'
#4660000
b1110101 T
b101 L
b1110101 (
1'
#4680000
0'
#4700000
b110 L
b1110110 T
b1110110 (
1'
#4720000
0'
#4740000
b1110111 T
b111 L
b1110111 (
1'
#4760000
0'
#4780000
b0 L
b1111000 T
b1111000 (
1'
#4800000
0'
#4820000
b1111001 T
1M
b1 L
b1111001 (
1'
#4840000
0'
#4860000
0M
b10 L
b1111010 T
b1111010 (
1'
#4880000
0'
#4900000
b1111011 T
b11 L
b1111011 (
1'
#4920000
0'
#4940000
b100 L
b1111100 T
b1111100 (
1'
#4960000
0'
#4980000
b1111101 T
b101 L
b1111101 (
1'
#5000000
0'
#5020000
b110 L
b1111110 T
b1111110 (
1'
#5040000
0'
#5060000
b1111111 T
b111 L
b1111111 (
1'
#5080000
0'
#5100000
b0 L
b10000000 T
b10000000 (
1'
#5120000
0'
#5140000
b10000001 T
1M
b1 L
b10000001 (
1'
#5160000
0'
#5180000
0M
b10 L
b10000010 T
b10000010 (
1'
#5200000
0'
#5220000
b10000011 T
b11 L
b10000011 (
1'
#5240000
0'
#5260000
b100 L
b10000100 T
b10000100 (
1'
#5280000
0'
#5300000
b10000101 T
b101 L
b10000101 (
1'
#5320000
0'
#5340000
b110 L
b10000110 T
b10000110 (
1'
#5360000
0'
#5380000
b10000111 T
b111 L
b10000111 (
1'
#5400000
0'
#5420000
b0 L
b10001000 T
b10001000 (
1'
#5440000
0'
#5460000
b10001001 T
1M
b1 L
b10001001 (
1'
#5480000
0'
#5500000
0M
b10 L
b10001010 T
b10001010 (
1'
#5520000
0'
#5540000
b10001011 T
b11 L
b10001011 (
1'
#5560000
0'
#5580000
b100 L
b10001100 T
b10001100 (
1'
#5600000
0'
#5620000
b10001101 T
b101 L
b10001101 (
1'
#5640000
0'
#5660000
b110 L
b10001110 T
b10001110 (
1'
#5680000
0'
#5700000
b10001111 T
b111 L
b10001111 (
1'
#5720000
0'
#5740000
b0 L
b10010000 T
b10010000 (
1'
#5760000
0'
#5780000
b10010001 T
1M
b1 L
b10010001 (
1'
#5800000
0'
#5820000
0M
b10 L
b10010010 T
b10010010 (
1'
#5840000
0'
#5860000
b10010011 T
b11 L
b10010011 (
1'
#5880000
0'
#5900000
b100 L
b10010100 T
b10010100 (
1'
#5920000
0'
#5940000
b10010101 T
b101 L
b10010101 (
1'
#5960000
0'
#5980000
b110 L
b10010110 T
b10010110 (
1'
#6000000
0'
#6020000
b10010111 T
b111 L
b10010111 (
1'
#6040000
0'
#6060000
b0 L
b10011000 T
b10011000 (
1'
#6080000
0'
#6100000
b10011001 T
1M
b1 L
b10011001 (
1'
#6120000
0'
#6140000
0M
b10 L
b10011010 T
b10011010 (
1'
#6160000
0'
#6180000
b10011011 T
b11 L
b10011011 (
1'
#6200000
0'
#6220000
b100 L
b10011100 T
b10011100 (
1'
#6240000
0'
#6260000
b10011101 T
b101 L
b10011101 (
1'
#6280000
0'
#6300000
b110 L
b10011110 T
b10011110 (
1'
#6320000
0'
#6340000
b10011111 T
b111 L
b10011111 (
1'
#6360000
0'
#6380000
b0 L
b10100000 T
b10100000 (
1'
#6400000
0'
#6420000
b10100001 T
1M
b1 L
b10100001 (
1'
#6440000
0'
#6460000
0M
b10 L
b10100010 T
b10100010 (
1'
#6480000
0'
#6500000
b10100011 T
b11 L
b10100011 (
1'
#6520000
0'
#6540000
b100 L
b10100100 T
b10100100 (
1'
#6560000
0'
#6580000
b10100101 T
b101 L
b10100101 (
1'
#6600000
0'
#6620000
b110 L
b10100110 T
b10100110 (
1'
#6640000
0'
#6660000
b10100111 T
b111 L
b10100111 (
1'
#6680000
0'
#6700000
b0 L
b10101000 T
b10101000 (
1'
#6720000
0'
#6740000
b10101001 T
1M
b1 L
b10101001 (
1'
#6760000
0'
#6780000
0M
b10 L
b10101010 T
b10101010 (
1'
#6800000
0'
#6820000
b10101011 T
b11 L
b10101011 (
1'
#6840000
0'
#6860000
b100 L
b10101100 T
b10101100 (
1'
#6880000
0'
#6900000
b10101101 T
b101 L
b10101101 (
1'
#6920000
0'
#6940000
b110 L
b10101110 T
b10101110 (
1'
#6960000
0'
#6980000
b10101111 T
b111 L
b10101111 (
1'
#7000000
0'
#7020000
b0 L
b10110000 T
b10110000 (
1'
#7040000
0'
#7060000
b10110001 T
1M
b1 L
b10110001 (
1'
#7080000
0'
#7100000
0M
b10 L
b10110010 T
b10110010 (
1'
#7120000
0'
#7140000
b10110011 T
b11 L
b10110011 (
1'
#7160000
0'
#7180000
b100 L
b10110100 T
b10110100 (
1'
#7200000
0'
#7220000
b10110101 T
b101 L
b10110101 (
1'
#7240000
0'
#7260000
b110 L
b10110110 T
b10110110 (
1'
#7280000
0'
#7300000
b10110111 T
b111 L
b10110111 (
1'
#7320000
0'
#7340000
b0 L
b10111000 T
b10111000 (
1'
#7360000
0'
#7380000
b10111001 T
1M
b1 L
b10111001 (
1'
#7400000
0'
#7420000
0M
b10 L
b10111010 T
b10111010 (
1'
#7440000
0'
#7460000
b10111011 T
b11 L
b10111011 (
1'
#7480000
0'
#7500000
b100 L
b10111100 T
b10111100 (
1'
#7520000
0'
#7540000
b10111101 T
b101 L
b10111101 (
1'
#7560000
0'
#7580000
b110 L
b10111110 T
b10111110 (
1'
#7600000
0'
#7620000
b10111111 T
b111 L
b10111111 (
1'
#7640000
0'
#7660000
b0 L
b11000000 T
b11000000 (
1'
#7680000
0'
#7700000
b11000001 T
1M
b1 L
b11000001 (
1'
#7720000
0'
#7740000
0M
b10 L
b11000010 T
b11000010 (
1'
#7760000
0'
#7780000
b11000011 T
b11 L
b11000011 (
1'
#7800000
0'
#7820000
b100 L
b11000100 T
b11000100 (
1'
#7840000
0'
#7860000
b11000101 T
b101 L
b11000101 (
1'
#7880000
0'
#7900000
b110 L
b11000110 T
b11000110 (
1'
#7920000
0'
#7940000
b11000111 T
b111 L
b11000111 (
1'
#7960000
0'
#7980000
b0 L
b11001000 T
b11001000 (
1'
#8000000
0'
#8020000
b11001001 T
1M
b1 L
b11001001 (
1'
#8040000
0'
#8060000
0M
b10 L
b11001010 T
b11001010 (
1'
#8080000
0'
#8100000
b11001011 T
b11 L
b11001011 (
1'
#8120000
0'
#8140000
b100 L
b11001100 T
b11001100 (
1'
#8160000
0'
#8180000
b11001101 T
b101 L
b11001101 (
1'
#8200000
0'
#8220000
b110 L
b11001110 T
b11001110 (
1'
#8240000
0'
#8260000
b11001111 T
b111 L
b11001111 (
1'
#8280000
0'
#8300000
b0 L
b11010000 T
b11010000 (
1'
#8320000
0'
#8340000
b11010001 T
1M
b1 L
b11010001 (
1'
#8360000
0'
#8380000
0M
b10 L
b11010010 T
b11010010 (
1'
#8400000
0'
#8420000
b11010011 T
b11 L
b11010011 (
1'
#8440000
0'
#8460000
b100 L
b11010100 T
b11010100 (
1'
#8480000
0'
#8500000
b11010101 T
b101 L
b11010101 (
1'
#8520000
0'
#8540000
b110 L
b11010110 T
b11010110 (
1'
#8560000
0'
#8580000
b11010111 T
b111 L
b11010111 (
1'
#8600000
0'
#8620000
b0 L
b11011000 T
b11011000 (
1'
#8640000
0'
#8660000
b11011001 T
1M
b1 L
b11011001 (
1'
#8680000
0'
#8700000
0M
b10 L
b11011010 T
b11011010 (
1'
#8720000
0'
#8740000
b11011011 T
b11 L
b11011011 (
1'
#8760000
0'
#8780000
b100 L
b11011100 T
b11011100 (
1'
#8800000
0'
#8820000
b11011101 T
b101 L
b11011101 (
1'
#8840000
0'
#8860000
b110 L
b11011110 T
b11011110 (
1'
#8880000
0'
#8900000
b11011111 T
b111 L
b11011111 (
1'
#8920000
0'
#8940000
b0 L
b11100000 T
b11100000 (
1'
#8960000
0'
#8980000
b11100001 T
1M
b1 L
b11100001 (
1'
#9000000
0'
#9020000
0M
b10 L
b11100010 T
b11100010 (
1'
#9040000
0'
#9060000
b11100011 T
b11 L
b11100011 (
1'
#9080000
0'
#9100000
b100 L
b11100100 T
b11100100 (
1'
#9120000
0'
#9140000
b11100101 T
b101 L
b11100101 (
1'
#9160000
0'
#9180000
b110 L
b11100110 T
b11100110 (
1'
#9200000
0'
#9220000
b11100111 T
b111 L
b11100111 (
1'
#9240000
0'
#9260000
b0 L
b11101000 T
b11101000 (
1'
#9280000
0'
#9300000
b11101001 T
1M
b1 L
b11101001 (
1'
#9320000
0'
#9340000
0M
b10 L
b11101010 T
b11101010 (
1'
#9360000
0'
#9380000
b11101011 T
b11 L
b11101011 (
1'
#9400000
0'
#9420000
b100 L
b11101100 T
b11101100 (
1'
#9440000
0'
#9460000
b11101101 T
b101 L
b11101101 (
1'
#9480000
0'
#9500000
b110 L
b11101110 T
b11101110 (
1'
#9520000
0'
#9540000
b11101111 T
b111 L
b11101111 (
1'
#9560000
0'
#9580000
b0 L
b11110000 T
b11110000 (
1'
#9600000
0'
#9620000
b11110001 T
1M
b1 L
b11110001 (
1'
#9640000
0'
#9660000
0M
b10 L
b11110010 T
b11110010 (
1'
#9680000
0'
#9700000
b11110011 T
b11 L
b11110011 (
1'
#9720000
0'
#9740000
b100 L
b11110100 T
b11110100 (
1'
#9760000
0'
#9780000
b11110101 T
b101 L
b11110101 (
1'
#9800000
0'
#9820000
b110 L
b11110110 T
b11110110 (
1'
#9840000
0'
