Calculadora_Verilog/control.v
module control_sqrt(clk, rst, init, msb, z, done, ld_tmp, r0, sh, ld, lda2);
    input clk, rst, init, msb, z;
    output reg done, ld_tmp, r0, sh, ld, lda2;

    parameter INICIO=0, VERIFICAR=1, DESPLAZAR=2, CARGAR_TMP=3, CARGAR_A2=4, VERIFICAR_Z=5, FINAL=6;
    reg [2:0] estado;

    always @(posedge clk) begin
        if (rst) begin
            estado <= INICIO;
        end else begin
            case(estado)
                INICIO: estado <= init ? DESPLAZAR : INICIO;
                DESPLAZAR: estado <= CARGAR_TMP;
                CARGAR_TMP: estado <= VERIFICAR;
                VERIFICAR: estado <= msb ? VERIFICAR_Z : CARGAR_A2;
                CARGAR_A2: estado <= VERIFICAR_Z;
                VERIFICAR_Z: estado <= z ? FINAL : DESPLAZAR;
                FINAL: estado <= FINAL;
                default: estado <= INICIO;
            endcase
        end
    end

    always @(*) begin
        {done, ld_tmp, r0, sh, ld, lda2} = 6'b000000;
        case(estado)
            INICIO: {ld} = 1'b1;
            DESPLAZAR: {sh} = 1'b1;
            CARGAR_TMP: {ld_tmp} = 1'b1;
            CARGAR_A2: {r0, lda2} = 2'b11;
            FINAL: {done} = 1'b1;
        endcase
    end
endmodule

Calculadora_Verilog/Raiz cuadrada/count.v
module count(clk, ld, dec, z);
    input clk, ld, dec;
    output reg z;
    reg [3:0] contador = 8;
    always @(negedge clk) begin
        if (ld) contador <= 8;
        else if (dec) contador <= contador - 1;
        z <= (contador == 0);
    end
endmodule

Calculadora_Verilog/addc2.v
module addc2(in_A, in_B, Result);
    input [15:0] in_A, in_B;
    output reg [15:0] Result;
    always @(*) Result = in_A + (~in_B) + 1;
endmodule

Calculadora_Verilog/Raiz cuadrada/lsr.v
module lsr(clk, reset, shift, load, load_R0, in_bit, in_A, out_r);
    input clk, reset, shift, load, load_R0, in_bit;
    input [15:0] in_A;
    output reg [15:0] out_r;
    always @(negedge clk) begin
        if (reset) out_r <= 0;
        else if (load) out_r <= in_A;
        else if (shift) out_r <= {out_r[14:0], 1'b0};
        else if (load_R0) out_r <= {out_r[15:1], in_bit};
    end
endmodule

Calculadora_Verilog/Raiz cuadrada/lsr2.v
module lsr2(clk, rst_ld, shift, lda2, in_R1, in_R2, out_R);
    input clk, rst_ld, shift, lda2;
    input [15:0] in_R1, in_R2;
    output [15:0] out_R;
    reg [31:0] datos;
    assign out_R = datos[31:16];
    always @(negedge clk) begin
        if (rst_ld) datos <= {16'h0000, in_R1};
        else if (shift) datos <= {datos[29:0], 2'b00};
        else if (lda2) datos[31:16] <= in_R2;
    end
endmodule

Calculadora_Verilog/Raiz cuadrada/sqrt.v
module sqrt(clk, rst, init, A, result, done);
    input clk;
    input rst;
    input init;
    input [15:0] A;
    output [15:0] result;
    output done;

    wire w_sh;
    wire w_ld;
    wire w_lda2;
    wire w_ld_tmp;
    wire w_z;
    wire w_r0;

    wire [15:0] w_tmp;
    wire [15:0] w_lda_out;
    wire [15:0] w_lda2_in;

    lsr2 lsr20(.clk(clk), .rst_ld(w_ld), .shift(w_sh), .lda2(w_lda2), .in_R1(A), .in_R2(w_lda2_in), .out_R(w_lda_out));
    lsr lsr_R(.clk(clk), .reset(w_ld), .in_A(16'h0000), .shift(w_sh), .load(1'b0), .load_R0(w_lda2), .in_bit(w_r0), .out_r(result));
    lsr lsr_TMP(.clk(clk), .reset(w_ld), .in_A(result), .shift(1'b0), .load(w_ld_tmp), .load_R0(1'b0), .in_bit(1'b0), .out_r(w_tmp));
    addc2 addsub0(.in_A(w_lda_out), .in_B({w_tmp[14:0], 1'b1}), .Result(w_lda2_in));
    count count0(.clk(clk), .ld(w_ld), .dec(w_sh), .z(w_z));
    control_sqrt control0(.clk(clk), .rst(rst), .init(init), .msb(w_lda2_in[15]), .z(w_z), .done(done), .ld_tmp(w_ld_tmp), .r0(w_r0), .sh(w_sh), .ld(w_ld), .lda2(w_lda2));

endmodule

Calculadora_Verilog/sqrt_TB.v
`timescale 1ns / 1ps
module sqrt_TB;
    reg clk, rst, start;
    reg [15:0] A;
    wire [15:0] result;
    wire done;

    sqrt uut(clk, rst, start, A, result, done);

    parameter PERIOD = 20;
    initial begin
        clk = 0;
        forever #(PERIOD/2) clk = ~clk;
    end

    initial begin
        rst = 0; start = 0; A = 16'h00E1;
        @(negedge clk); rst = 1;
        @(negedge clk); rst = 0;
        #(PERIOD*4);
        @(posedge clk); start = 1;
        @(posedge clk); start = 0;
        #(PERIOD*100);
        $finish;
    end

    initial begin
        $dumpfile("sqrt_TB.vcd");
        $dumpvars(0, sqrt_TB);
    end
endmodule

Calculadora_Verilog/Raiz cuadrada/sqrt_TB.vcd
$date
	Fri Nov 21 15:43:35 2025
$end
$version
	Icarus Verilog
$end
$timescale
	1ps
$end
$scope module sqrt_TB $end
$var wire 16 ! result [15:0] $end
$var wire 1 " done $end
$var parameter 32 # PERIOD $end
$var reg 16 $ A [15:0] $end
$var reg 1 % clk $end
$var reg 1 & rst $end
$var reg 1 ' start $end
$scope module uut $end
$var wire 16 ( A [15:0] $end
$var wire 1 % clk $end
$var wire 1 ' init $end
$var wire 1 & rst $end
$var wire 1 ) w_z $end
$var wire 16 * w_tmp [15:0] $end
$var wire 1 + w_sh $end
$var wire 1 , w_r0 $end
$var wire 16 - w_lda_out [15:0] $end
$var wire 16 . w_lda2_in [15:0] $end
$var wire 1 / w_lda2 $end
$var wire 1 0 w_ld_tmp $end
$var wire 1 1 w_ld $end
$var wire 16 2 result [15:0] $end
$var wire 1 " done $end
$scope module addsub0 $end
$var wire 16 3 in_B [15:0] $end
$var wire 16 4 in_A [15:0] $end
$var reg 16 5 Result [15:0] $end
$upscope $end
$scope module control0 $end
$var wire 1 % clk $end
$var wire 1 ' init $end
$var wire 1 6 msb $end
$var wire 1 & rst $end
$var wire 1 ) z $end
$var parameter 32 7 CARGAR_A2 $end
$var parameter 32 8 CARGAR_TMP $end
$var parameter 32 9 DESPLAZAR $end
$var parameter 32 : FINAL $end
$var parameter 32 ; INICIO $end
$var parameter 32 < VERIFICAR $end
$var parameter 32 = VERIFICAR_Z $end
$var reg 1 " done $end
$var reg 3 > estado [2:0] $end
$var reg 1 1 ld $end
$var reg 1 0 ld_tmp $end
$var reg 1 / lda2 $end
$var reg 1 , r0 $end
$var reg 1 + sh $end
$upscope $end
$scope module count0 $end
$var wire 1 % clk $end
$var wire 1 + dec $end
$var wire 1 1 ld $end
$var reg 4 ? contador [3:0] $end
$var reg 1 ) z $end
$upscope $end
$scope module lsr20 $end
$var wire 1 % clk $end
$var wire 16 @ in_R1 [15:0] $end
$var wire 16 A in_R2 [15:0] $end
$var wire 1 / lda2 $end
$var wire 1 1 rst_ld $end
$var wire 1 + shift $end
$var wire 16 B out_R [15:0] $end
$var reg 32 C datos [31:0] $end
$upscope $end
$scope module lsr_R $end
$var wire 1 % clk $end
$var wire 16 D in_A [15:0] $end
$var wire 1 , in_bit $end
$var wire 1 E load $end
$var wire 1 / load_R0 $end
$var wire 1 1 reset $end
$var wire 1 + shift $end
$var reg 16 F out_r [15:0] $end
$upscope $end
$scope module lsr_TMP $end
$var wire 1 % clk $end
$var wire 16 G in_A [15:0] $end
$var wire 1 H in_bit $end
$var wire 1 0 load $end
$var wire 1 I load_R0 $end
$var wire 1 1 reset $end
$var wire 1 J shift $end
$var reg 16 K out_r [15:0] $end
$upscope $end
$upscope $end
$upscope $end
$enddefinitions $end
$comment Show the parameter values. $end
$dumpall
b101 =
b1 <
b0 ;
b110 :
b10 9
b11 8
b100 7
b10100 #
$end
#0
$dumpvars
bx K
0J
0I
0H
bx G
bx F
0E
b0 D
bx C
bx B
bx A
b11100001 @
b1000 ?
bx >
x6
bx 5
bx 4
bx1 3
bx 2
x1
x0
x/
bx .
bx -
x,
x+
bx *
0)
b11100001 (
0'
0&
0%
b11100001 $
x"
bx !
$end
#10000
0"
00
0,
0+
11
0/
b0 >
1%
#20000
16
b1111111111111111 .
b1111111111111111 5
b1111111111111111 A
b1 3
b0 -
b0 4
b0 B
b0 *
b0 K
b0 !
b0 2
b0 F
b0 G
b11100001 C
1&
0%
#30000
1%
#40000
0&
0%
#50000
1%
#60000
0%
#70000
1%
#80000
0%
#90000
1%
#100000
0%
#110000
1%
#120000
0%
#130000
1+
01
b10 >
1'
1%
#140000
b111 ?
b1110000100 C
0%
#150000
10
0+
b11 >
0'
1%
#160000
0%
#170000
00
b1 >
1%
#180000
0%
#190000
b101 >
1%
#200000
0%
#210000
1+
b10 >
1%
#220000
b110 ?
b111000010000 C
0%
#230000
10
0+
b11 >
1%
#240000
0%
#250000
00
b1 >
1%
#260000
0%
#270000
b101 >
1%
#280000
0%
#290000
1+
b10 >
1%
#300000
b101 ?
b11100001000000 C
0%
#310000
10
0+
b11 >
1%
#320000
0%
#330000
00
b1 >
1%
#340000
0%
#350000
b101 >
1%
#360000
0%
#370000
1+
b10 >
1%
#380000
b100 ?
b1110000100000000 C
0%
#390000
10
0+
b11 >
1%
#400000
0%
#410000
00
b1 >
1%
#420000
0%
#430000
b101 >
1%
#440000
0%
#450000
1+
b10 >
1%
#460000
06
b10 .
b10 5
b10 A
b11 -
b11 4
b11 B
b11 ?
b111000010000000000 C
0%
#470000
10
0+
b11 >
1%
#480000
0%
#490000
00
b1 >
1%
#500000
0%
#510000
1,
1/
b100 >
1%
#520000
b1 .
b1 5
b1 A
b10 -
b10 4
b10 B
b101000010000000000 C
b1 !
b1 2
b1 F
b1 G
0%
#530000
0,
0/
b101 >
1%
#540000
0%
#550000
1+
b10 >
1%
#560000
b1001 .
b1001 5
b1001 A
b1010 -
b1010 4
b1010 B
b10100001000000000000 C
b10 !
b10 2
b10 F
b10 G
b10 ?
0%
#570000
10
0+
b11 >
1%
#580000
b101 .
b101 5
b101 A
b101 3
b10 *
b10 K
0%
#590000
00
b1 >
1%
#600000
0%
#610000
1,
1/
b100 >
1%
#620000
b0 .
b0 5
b0 A
b101 -
b101 4
b101 B
b11 !
b11 2
b11 F
b11 G
b1010001000000000000 C
0%
#630000
0,
0/
b101 >
1%
#640000
0%
#650000
1+
b10 >
1%
#660000
b1111 .
b1111 5
b1111 A
b10100 -
b10100 4
b10100 B
b1 ?
b110 !
b110 2
b110 F
b110 G
b101000100000000000000 C
0%
#670000
10
0+
b11 >
1%
#680000
b111 .
b111 5
b111 A
b1101 3
b110 *
b110 K
0%
#690000
00
b1 >
1%
#700000
0%
#710000
1,
1/
b100 >
1%
#720000
16
b1111111111111010 .
b1111111111111010 5
b1111111111111010 A
b111 -
b111 4
b111 B
b1110100000000000000 C
b111 !
b111 2
b111 F
b111 G
0%
#730000
0,
0/
b101 >
1%
#740000
0%
#750000
1+
b10 >
1%
#760000
06
b10000 .
b10000 5
b10000 A
b11101 -
b11101 4
b11101 B
b111010000000000000000 C
b1110 !
b1110 2
b1110 F
b1110 G
b0 ?
0%
#770000
10
0+
b11 >
1%
#780000
b0 .
b0 5
b0 A
b11101 3
1)
b1110 *
b1110 K
0%
#790000
00
b1 >
1%
#800000
0%
#810000
1,
1/
b100 >
1%
#820000
16
b1111111111100011 .
b1111111111100011 5
b1111111111100011 A
b0 -
b0 4
b0 B
b1111 !
b1111 2
b1111 F
b1111 G
b0 C
0%
#830000
0,
0/
b101 >
1%
#840000
0%
#850000
1"
b110 >
1%
